{
    "hyprNStack": {
        "cargoLocks": null,
        "date": null,
        "extract": null,
        "name": "hyprNStack",
        "passthru": null,
        "pinned": false,
        "src": {
            "deepClone": false,
            "fetchSubmodules": false,
            "leaveDotGit": false,
            "name": null,
            "owner": "zakk4223",
            "repo": "hyprNstack",
            "rev": "e05c16c9877c09820079b28899a6f9f4e76abd52",
            "sha256": "sha256-6PqHyXB5SHIhVuIN7Gkjn7RX5wfvBFINJYh4eLNkqIg=",
            "sparseCheckout": [],
            "type": "github"
        },
        "version": "e05c16c9877c09820079b28899a6f9f4e76abd52"
    }
}